blackwall/__init__.py
blackwall/main.py
blackwall/swarms_api_client.py
blackwall_gateway-1.0.1.dist-info/LICENSE
blackwall_gateway-1.0.1.dist-info/METADATA
blackwall_gateway-1.0.1.dist-info/WHEEL
blackwall_gateway-1.0.1.dist-info/RECORD
