Metadata-Version: 2.3
Name: blackwall-gateway
Version: 1.0.1
Summary: An intelligent API security middleware that monitors, detects, and blocks malicious threats in real-time. Built on the Swarms framework, Blackwall provides comprehensive protection against SQL injection, XSS, command injection, path traversal, SSRF, and other web application vulnerabilities. Features automated IP blocking, rate limiting, threat analytics, and AI-powered decision making for FastAPI applications.
License: Apache-2.0
Keywords: security,cybersecurity,api-security,threat-detection,web-security,sql-injection,xss,command-injection,rate-limiting,ip-blocking,fastapi,middleware,swarms,agents,ai-security,api-protection,threat-analysis,security-monitoring,automated-security,application-security,waf,web-application-firewall
Author: Kye Gomez
Author-email: kye@swarms.world
Requires-Python: >=3.10,<4.0
Classifier: Development Status :: 4 - Beta
Classifier: Intended Audience :: Developers
Classifier: License :: OSI Approved :: Apache Software License
Classifier: Programming Language :: Python :: 3
Classifier: Programming Language :: Python :: 3.10
Classifier: Programming Language :: Python :: 3.11
Classifier: Programming Language :: Python :: 3.12
Classifier: Programming Language :: Python :: 3.13
Classifier: Topic :: Internet :: WWW/HTTP :: HTTP Servers
Classifier: Topic :: Security
Classifier: Topic :: Software Development :: Libraries :: Python Modules
Requires-Dist: fastapi
Requires-Dist: httpx
Requires-Dist: loguru
Requires-Dist: pydantic
Requires-Dist: requests
Requires-Dist: starlette
Requires-Dist: swarms
Requires-Dist: uvicorn
